addcart_properties_pkg/__init__.py
addcart_properties_pkg/addcart.py
19226331LalitAgrawal-0.0.1.dist-info/LICENSE
19226331LalitAgrawal-0.0.1.dist-info/METADATA
19226331LalitAgrawal-0.0.1.dist-info/WHEEL
19226331LalitAgrawal-0.0.1.dist-info/top_level.txt
19226331LalitAgrawal-0.0.1.dist-info/RECORD
