Metadata-Version: 2.1
Name: 19226331LalitAgrawal
Version: 0.0.1
Summary: A package to calculate total cart value
Home-page: https://github.com/agrawallalit/Food_ordering_library
Author: Lalit Agrawal
Author-email: agrawal.lalit95@gmail.com
License: UNKNOWN
Platform: UNKNOWN
Classifier: Programming Language :: Python :: 3
Classifier: License :: OSI Approved :: MIT License
Classifier: Operating System :: OS Independent
Requires-Python: >=3.6
License-File: LICENSE
